pycapt/__init__.py
pycapt/basic/__init__.py
pycapt/basic/reset_file_type.py
pycapt/basic/resize_img.py
pycapt/logo/__init__.py
pycapt/logo/android_logo.py
pycapt/logo/ios_logo.py
pycapt/make_captcha/__init__.py
pycapt/make_captcha/easy_mode.py
pycapt/make_captcha/make_capt.py
pycapt/make_captcha/my_any_img.py
pycapt/make_captcha/noise.py
pycapt/solve_it/__init__.py
pycapt/solve_it/cut_img.py
pycapt/solve_it/de_line.py
pycapt/solve_it/de_point.py
pycapt/solve_it/easy_solve.py
pycapt-1.0.20.dist-info/LICENSE
pycapt-1.0.20.dist-info/METADATA
pycapt-1.0.20.dist-info/WHEEL
pycapt-1.0.20.dist-info/top_level.txt
pycapt-1.0.20.dist-info/RECORD
