Metadata-Version: 2.1
Name: pycapt
Version: 1.0.20
Summary: a library that processes verification codes
Home-page: https://github.com/aboutmydreams/pycapt
Author: aboutmydreams
Author-email: aboutmydreams@163.com
Classifier: Programming Language :: Python :: 3
Classifier: License :: OSI Approved :: MIT License
Classifier: Operating System :: OS Independent
License-File: LICENSE
